rejd/__init__.py
rejd/transformer.py
rejd-0.0.1.dist-info/LICENSE
rejd-0.0.1.dist-info/METADATA
rejd-0.0.1.dist-info/WHEEL
rejd-0.0.1.dist-info/top_level.txt
rejd-0.0.1.dist-info/RECORD
