Metadata-Version: 2.1
Name: rejd
Version: 0.0.1
Summary: ReJD (Representation JSON Data) - Python library that change your "JSON like" data representation.
Home-page: https://github.com/rejd-tools/rejd-python
Author: Vadim Sharay
Author-email: vadimsharay@gmail.com
Maintainer: Vadim Sharay
Maintainer-email: vadimsharay@gmail.com
License: Apache License, Version 2.0
Keywords: json library python3 python transform representation rejd
Platform: UNKNOWN
Classifier: Development Status :: 3 - Alpha
Classifier: License :: OSI Approved :: Apache Software License
Classifier: Operating System :: OS Independent
Classifier: Programming Language :: Python :: 3.5
Classifier: Programming Language :: Python :: 3.6
Classifier: Programming Language :: Python :: 3.7
Classifier: Programming Language :: Python :: 3.8
Classifier: Programming Language :: Python :: 3.9
Classifier: Programming Language :: Python :: Implementation :: PyPy
Classifier: Intended Audience :: Developers
Classifier: Topic :: Software Development :: Libraries :: Python Modules
Classifier: Topic :: Utilities
Requires-Python: >=3.5
License-File: LICENSE
Requires-Dist: jsonpath-ng (~=1.5)
Provides-Extra: dev
Requires-Dist: black (~=22.3) ; extra == 'dev'
Requires-Dist: flake8 (~=4.0) ; extra == 'dev'
Requires-Dist: pre-commit (~=2.18) ; extra == 'dev'
Requires-Dist: pytest (~=7.1) ; extra == 'dev'
